setup.py
tr8cks/Client.py
tr8cks/__init__.py
tr8cks.egg-info/PKG-INFO
tr8cks.egg-info/SOURCES.txt
tr8cks.egg-info/dependency_links.txt
tr8cks.egg-info/not-zip-safe
tr8cks.egg-info/requires.txt
tr8cks.egg-info/top_level.txt