Metadata-Version: 1.0
Name: tr8cks
Version: 0.1.4
Summary: Python wrapper for the 8tracks.com ReSTful API
Home-page: https://github.com/wh1tney/tr8cks
Author: Whitney O'Banner
Author-email: wobanner@gmail.com
License: UNKNOWN
Platform: UNKNOWN
